spotidex/__init__.py
spotidex/cli/__init__.py
spotidex/cli/app_screens/__init__.py
spotidex/cli/app_screens/DownloadInterface.py
spotidex/cli/app_screens/MainMenuInterface.py
spotidex/cli/app_screens/SearchInterface.py
spotidex/cli/app_screens/SelectDownloadInterface.py
spotidex/cli/app_screens/SettingsInterface.py
spotidex/cli/custom_widgets/__init__.py
spotidex/cli/custom_widgets/AppInterface.py
spotidex/cli/custom_widgets/DownloadPathSelector.py
spotidex/cli/custom_widgets/DownloadQualitySelection.py
spotidex/cli/custom_widgets/MetadataCheckBox.py
spotidex/cli/popup_screens/__init__.py
spotidex/cli/popup_screens/DownloadPathPopup.py
spotidex/cli/popup_screens/ExitScreenPopup.py
spotidex/cli/popup_screens/GoBackSettingsPopup.py
spotidex/cli/popup_screens/NetworkErrorPopup.py
spotidex/cli/SpotidexApp.py
spotidex/cli/utils.py
spotidex/src/__init__.py
spotidex/src/content.py
spotidex/src/download.py
spotidex/src/static.py
spotidex/src/utils.py
spotidex-1.0.0.dist-info/entry_points.txt
spotidex-1.0.0.dist-info/METADATA
spotidex-1.0.0.dist-info/WHEEL
spotidex-1.0.0.dist-info/RECORD
